text_quality/__init__.py
text_quality/settings.py
text_quality/classifier/__init__.py
text_quality/classifier/pipeline.py
text_quality/data/classifier/pipeline_nn.joblib
text_quality/data/dicts/lb.txt
text_quality/data/dicts/nl_voc.txt
text_quality/data/dicts/hunspell/de.aff
text_quality/data/dicts/hunspell/de.dic
text_quality/data/dicts/hunspell/fr.aff
text_quality/data/dicts/hunspell/fr.dic
text_quality/data/dicts/hunspell/nl.aff
text_quality/data/dicts/hunspell/nl.dic
text_quality/data/qgrams/nl_voc.txt
text_quality/feature/__init__.py
text_quality/feature/featurize.py
text_quality/feature/tokenizer.py
text_quality/feature/scorer/__init__.py
text_quality/feature/scorer/dictionary.py
text_quality/feature/scorer/garbage.py
text_quality/feature/scorer/q_gram.py
text_quality/feature/scorer/scorer.py
text_quality/language/__init__.py
text_quality/language/classifier.py
text_quality/language/fasttext.py
text_quality/page/__init__.py
text_quality/page/page.py
text_quality-0.3.1.data/scripts/classify_text_quality.py
text_quality-0.3.1.dist-info/LICENSE
text_quality-0.3.1.dist-info/LICENSE_NL_OPENTAAL.txt
text_quality-0.3.1.dist-info/METADATA
text_quality-0.3.1.dist-info/NOTICE
text_quality-0.3.1.dist-info/WHEEL
text_quality-0.3.1.dist-info/top_level.txt
text_quality-0.3.1.dist-info/RECORD
