Metadata-Version: 2.1
Name: text-quality
Version: 0.3.1
Summary: A package to determine the quality of a a digitized text, from a handwritten script or scanned print (HTR/OCR output).
Home-page: https://github.com/laHTeR/htr-quality-classifier
Author: Carsten Schnober
Author-email: c.schnober@esciencecenter.nl
Project-URL: Bug Tracker, https://github.com/laHTeR/htr-quality-classifier/issues
Keywords: htr,ocr
Classifier: Development Status :: 3 - Alpha
Classifier: Intended Audience :: Developers
Classifier: License :: OSI Approved :: GNU General Public License v3 (GPLv3)
Classifier: Natural Language :: English
Classifier: Programming Language :: Python :: 3
Classifier: Programming Language :: Python :: 3.9
Classifier: Programming Language :: Python :: 3.10
Classifier: Programming Language :: Python :: 3.11
Requires-Python: >=3.9
License-File: LICENSE
License-File: LICENSE_NL_OPENTAAL.txt
License-File: NOTICE
Requires-Dist: fasttext-wheel ~=0.9.2
Requires-Dist: joblib ~=1.2.0
Requires-Dist: pandas <3.0.0,>=1.5.3
Requires-Dist: pagexml-tools ~=0.4.1
Requires-Dist: scikit-learn ~=1.2.1
Requires-Dist: spylls ~=0.1.7
Requires-Dist: tqdm >=4.65.0
Requires-Dist: openpyxl ~=3.1.2
Provides-Extra: dev
Requires-Dist: bump2version ; extra == 'dev'
Requires-Dist: coverage[toml] ; extra == 'dev'
Requires-Dist: prospector[with_pyroma] ; extra == 'dev'
Requires-Dist: isort ; extra == 'dev'
Requires-Dist: pytest ; extra == 'dev'
Requires-Dist: pytest-cov ; extra == 'dev'
Requires-Dist: sphinx ; extra == 'dev'
Requires-Dist: sphinx-rtd-theme ; extra == 'dev'
Requires-Dist: sphinx-autoapi ; extra == 'dev'
Requires-Dist: tox ; extra == 'dev'
Requires-Dist: myst-parser ; extra == 'dev'
Provides-Extra: publishing
Requires-Dist: twine ; extra == 'publishing'
Requires-Dist: wheel ; extra == 'publishing'
